spiel_des_jahres/__init__.py
spiel_des_jahres/data/2024/reviews.csv
spiel_des_jahres/data/2025/exclude.csv
spiel_des_jahres/data/2025/reviews.csv
spiel_des_jahres/data/kindersdj.csv
spiel_des_jahres/data/kritikenrundschau.csv
spiel_des_jahres/data/ksdj.csv
spiel_des_jahres/data/sdj.csv
spiel_des_jahres/data.py
spiel_des_jahres/kennerspiel/__init__.py
spiel_des_jahres/kennerspiel/__main__.py
spiel_des_jahres/llm_pipeline.py
spiel_des_jahres/predictions.py
spiel_des_jahres/py.typed
spiel_des_jahres/ratings.py
spiel_des_jahres/review_spider.py
spiel_des_jahres/utils.py
spiel_des_jahres-0.3.1.dist-info/LICENSE
spiel_des_jahres-0.3.1.dist-info/METADATA
spiel_des_jahres-0.3.1.dist-info/WHEEL
spiel_des_jahres-0.3.1.dist-info/RECORD
