Metadata-Version: 2.1
Name: spiel-des-jahres
Version: 0.3.1
Summary: Spiel des Jahres predictions
Home-page: https://recommend-games.github.io/spiel-des-jahres
License: MIT
Author: Markus Shepherd
Author-email: markus@recommend.games
Requires-Python: >=3.10.0,<4.0
Classifier: Development Status :: 4 - Beta
Classifier: Intended Audience :: Developers
Classifier: License :: OSI Approved :: MIT License
Classifier: Operating System :: OS Independent
Classifier: Programming Language :: Python
Classifier: Programming Language :: Python :: 3
Classifier: Programming Language :: Python :: 3.10
Classifier: Programming Language :: Python :: 3.11
Classifier: Programming Language :: Python :: 3.12
Classifier: Programming Language :: Python :: 3.13
Classifier: Topic :: Software Development :: Libraries :: Python Modules
Classifier: Typing :: Typed
Provides-Extra: kennerspiel
Provides-Extra: predictions
Provides-Extra: scraper
Requires-Dist: beautifulsoup4 (>=4.12.0,<5.0) ; extra == "scraper"
Requires-Dist: board-game-recommender (>=4.0.0,<5.0) ; extra == "predictions"
Requires-Dist: funcy (>=2.0.0,<3.0.0) ; extra == "kennerspiel" or extra == "predictions"
Requires-Dist: joblib (>=1.0.0,<2.0.0) ; extra == "kennerspiel" or extra == "predictions"
Requires-Dist: numpy (>=2.0.0,<3.0.0) ; extra == "kennerspiel" or extra == "predictions"
Requires-Dist: openai (>=1.0.0,<2.0.0) ; extra == "scraper"
Requires-Dist: pandas (>=2.0.0,<3.0.0) ; extra == "kennerspiel" or extra == "predictions"
Requires-Dist: polars[pandas,pyarrow] (>=1.0.0,<2.0.0) ; extra == "kennerspiel" or extra == "predictions" or extra == "scraper"
Requires-Dist: scikit-learn (>=1.0.0,<2.0.0) ; extra == "kennerspiel" or extra == "predictions"
Requires-Dist: scipy (>=1.0.0,<2.0.0) ; extra == "kennerspiel" or extra == "predictions"
Requires-Dist: scrapy (>=2.11.0,<3.0) ; extra == "scraper"
Requires-Dist: tqdm ; extra == "predictions"
Project-URL: Documentation, https://recommend-games.github.io/spiel-des-jahres
Project-URL: Repository, https://github.com/recommend-games/spiel-des-jahres
